[
    {
        "tur": "live",
        "type": "futbol",
        "name": "Club America - Club Tijuana Xoloitzcuintles de Caliente",
        "time": "04:00",
        "id": "275005219270692864"
    },
    {
        "tur": "live",
        "type": "futbol",
        "name": "Botafogo RJ - EC Vitoria",
        "time": "03:30",
        "id": "274393682928603136"
    },
    {
        "tur": "live",
        "type": "futbol",
        "name": "Bragantino Red Bull - Sao Paulo FC",
        "time": "03:30",
        "id": "274394044940029952"
    },
    {
        "tur": "live",
        "type": "futbol",
        "name": "Nashville SC - Columbus Crew",
        "time": "03:30",
        "id": "275596766436528128"
    },
    {
        "tur": "live",
        "type": "futbol",
        "name": "Minnesota United - Los Angeles FC",
        "time": "03:30",
        "id": "275606295585886208"
    },
    {
        "tur": "live",
        "type": "futbol",
        "name": "Houston Dynamo - Vancouver Whitecaps",
        "time": "03:30",
        "id": "275602570698952704"
    },
    {
        "tur": "live",
        "type": "futbol",
        "name": "San Antonio Bulo Bulo - Once Caldas",
        "time": "03:30",
        "id": "271846496049172480"
    },
    {
        "tur": "live",
        "type": "futbol",
        "name": "Alianza Lima - Gremio Porto Alegrense RS",
        "time": "03:30",
        "id": "271846497404981248"
    },
    {
        "tur": "live",
        "type": "futbol",
        "name": "Tulsa Roughnecks FC - Monterey Bay",
        "time": "03:30",
        "id": "275619404261232640"
    },
    {
        "tur": "live",
        "type": "futbol",
        "name": "Orlando City SC - New York City FC",
        "time": "03:15",
        "id": "275595160594812928"
    },
    {
        "tur": "live",
        "type": "futbol",
        "name": "St Louis City II - Ventura County",
        "time": "03:00",
        "id": "275679261312028672"
    },
    {
        "tur": "live",
        "type": "futbol",
        "name": "Forward Madison FC - Charlotte Independence",
        "time": "03:00",
        "id": "275820966870913024"
    },
    {
        "tur": "live",
        "type": "futbol",
        "name": "Venezuela (Kadınlar) - Kolombiya (Kadınlar)",
        "time": "03:00",
        "id": "275765832658849792"
    },
    {
        "tur": "live",
        "type": "futbol",
        "name": "Olmedo - LDU Quito ",
        "time": "03:00",
        "id": "275679276319248384"
    },
    {
        "tur": "live",
        "type": "futbol",
        "name": "Ristozi FC - Jackson Lions",
        "time": "02:00",
        "id": "275942831579860992"
    }
]