[
    {
        "tur": "live",
        "type": "futbol",
        "name": "Gold Coast Knights (W) - Brisbane City (W)",
        "time": "09:30",
        "id": "280956554747973632"
    },
    {
        "tur": "live",
        "type": "futbol",
        "name": "Heidelberg United (W) - Box Hill United (W)",
        "time": "09:00",
        "id": "280937589944487936"
    },
    {
        "tur": "live",
        "type": "futbol",
        "name": "Belconnen United - Australian National University FC",
        "time": "09:00",
        "id": "281020740383412224"
    },
    {
        "tur": "live",
        "type": "futbol",
        "name": "Maruyasu Industries SC - Grulla Morioka",
        "time": "09:00",
        "id": "281045121154289664"
    },
    {
        "tur": "live",
        "type": "futbol",
        "name": "Minebea Mitsumi - Briobecca Urayasu SC",
        "time": "09:00",
        "id": "280822899042029568"
    },
    {
        "tur": "live",
        "type": "futbol",
        "name": "Inter Taoyuan FC - AC Taipei Reserves",
        "time": "09:00",
        "id": "281163481804312576"
    },
    {
        "tur": "live",
        "type": "futbol",
        "name": "Consadole Sapporo - Iwaki SC",
        "time": "08:00",
        "id": "280608005597302784"
    },
    {
        "tur": "live",
        "type": "futbol",
        "name": "Jeonbuk Motors II - Mokpo City",
        "time": "08:00",
        "id": "280972393212678144"
    },
    {
        "tur": "live",
        "type": "futbol",
        "name": "Changwon City - Gangneung City",
        "time": "08:00",
        "id": "280752847655669760"
    }
]