[
    {
        "tur": "live",
        "type": "futbol",
        "name": "Cerro Porteno - Deportivo Recoleta",
        "time": "02:00",
        "id": "282761266328801280"
    },
    {
        "tur": "live",
        "type": "futbol",
        "name": "Argentino Merlo - CA Fenix",
        "time": "02:00",
        "id": "282738672734081024"
    },
    {
        "tur": "live",
        "type": "futbol",
        "name": "South Georgia Tormenta FC - Westchester SC",
        "time": "02:00",
        "id": "282658897113780224"
    },
    {
        "tur": "live",
        "type": "futbol",
        "name": "Charlotte Independence - Spokane Velocity FC",
        "time": "02:00",
        "id": "282659559590465536"
    },
    {
        "tur": "live",
        "type": "futbol",
        "name": "Queretaro (W) - Necaxa (W)",
        "time": "02:00",
        "id": "282650676133236736"
    },
    {
        "tur": "live",
        "type": "futbol",
        "name": "CD Tapatio - Alebrijes Oaxaca",
        "time": "02:00",
        "id": "282478007250194432"
    },
    {
        "tur": "live",
        "type": "futbol",
        "name": "Sao Paulo (W) - San Lorenzo (W)",
        "time": "02:00",
        "id": "283056716752654336"
    },
    {
        "tur": "live",
        "type": "futbol",
        "name": "CA Rentistas - Centro Atletico Fenix Montevideo",
        "time": "01:45",
        "id": "282871335862177792"
    },
    {
        "tur": "live",
        "type": "futbol",
        "name": "Deportes Concepcion - Magallanes",
        "time": "01:30",
        "id": "282295547590742016"
    },
    {
        "tur": "live",
        "type": "futbol",
        "name": "Tigre - Defensa y Justicia",
        "time": "01:00",
        "id": "282458760872595456"
    },
    {
        "tur": "live",
        "type": "futbol",
        "name": "Athletic Club MG - Amazonas FC",
        "time": "01:00",
        "id": "282606136448913408"
    },
    {
        "tur": "live",
        "type": "futbol",
        "name": "Boca Juniors Cali - Bogota FC",
        "time": "01:00",
        "id": "282655266976174080"
    },
    {
        "tur": "live",
        "type": "futbol",
        "name": "Montevideo City Torque - Miramar Misiones",
        "time": "01:00",
        "id": "282461057408176128"
    },
    {
        "tur": "live",
        "type": "futbol",
        "name": "Club Mercedes - Deportivo Paraguayo",
        "time": "00:30",
        "id": "282824949976305664"
    },
    {
        "tur": "live",
        "type": "futbol",
        "name": "Universitario De Vinto - CDT Real Oruro",
        "time": "00:30",
        "id": "282870087812419584"
    }
]