[
    {
        "tur": "live",
        "type": "futbol",
        "name": "Throttur Reykjavik - Fjolnir Reykjavik",
        "time": "22:15",
        "id": "273296707638398976"
    },
    {
        "tur": "live",
        "type": "futbol",
        "name": "Vaengir Jupiters - Hafnir",
        "time": "22:15",
        "id": "273331979509960704"
    },
    {
        "tur": "live",
        "type": "futbol",
        "name": "Hamar Hveragerdi - Alftanes",
        "time": "22:15",
        "id": "273332093586640896"
    },
    {
        "tur": "live",
        "type": "futbol",
        "name": "FC Arbaer - Ymir",
        "time": "22:15",
        "id": "273260166464540672"
    },
    {
        "tur": "live",
        "type": "futbol",
        "name": "Grotta (W) - Afturelding\/Fram (W)",
        "time": "22:15",
        "id": "273330182226579456"
    },
    {
        "tur": "live",
        "type": "futbol",
        "name": "Haukar Hafnafjordur (W) - Kr Reykjavik",
        "time": "22:15",
        "id": "273330847513448448"
    },
    {
        "tur": "live",
        "type": "futbol",
        "name": "Fylkir Reykjavik (W) - HK Kopavogur (W)",
        "time": "22:15",
        "id": "273330847625646080"
    },
    {
        "tur": "live",
        "type": "futbol",
        "name": "Inter Miami CF - FC Porto",
        "time": "22:00",
        "id": "272636500764659712"
    },
    {
        "tur": "live",
        "type": "futbol",
        "name": "Al Quwa\/Jawiya - Erbil SC",
        "time": "21:30",
        "id": "273142432654299136"
    },
    {
        "tur": "live",
        "type": "futbol",
        "name": "Al Kahrabaa Club - Al Naft",
        "time": "21:30",
        "id": "273142432959434752"
    },
    {
        "tur": "live",
        "type": "futbol",
        "name": "Liverpool FC Montevideo - Penarol Montevideo",
        "time": "21:00",
        "id": "273128199980978176"
    },
    {
        "tur": "live",
        "type": "futbol",
        "name": "Internacional Rs U20 - Cruzeiro EC U20",
        "time": "21:00",
        "id": "273218756550987776"
    },
    {
        "tur": "live",
        "type": "futbol",
        "name": "Treze FC PB - Santa Cruz de Natal",
        "time": "21:00",
        "id": "273173471855513600"
    },
    {
        "tur": "live",
        "type": "futbol",
        "name": "Aasane Fotball II - Loddefjord",
        "time": "21:00",
        "id": "273142426846236672"
    },
    {
        "tur": "live",
        "type": "futbol",
        "name": "Bollstanas SK - FC Jarfalla",
        "time": "21:00",
        "id": "273218044913913856"
    }
]