[
    {
        "tur": "live",
        "type": "futbol",
        "name": "Deportivo Marquense - CSD Comunicaciones",
        "time": "02:30",
        "id": "268882929809231872"
    },
    {
        "tur": "live",
        "type": "futbol",
        "name": "Oceania FC - FC Politecnico",
        "time": "01:00",
        "id": "269026714439520256"
    },
    {
        "tur": "live",
        "type": "futbol",
        "name": "Botafogo PB - Flamengo RJ",
        "time": "02:00",
        "id": "267634655157686272"
    },
    {
        "tur": "live",
        "type": "futbol",
        "name": "Corinthians Paulista (Kadınlar) - Gremio RS (W)",
        "time": "01:00",
        "id": "268623223657205760"
    },
    {
        "tur": "live",
        "type": "basketbol",
        "name": "Detroit Pistons - New York Knicks",
        "time": "02:30",
        "id": "268901009953263616"
    },
    {
        "tur": "live",
        "type": "basketbol",
        "name": "Franca BC - Pato Basquete",
        "time": "01:00",
        "id": "268906989250285568"
    },
    {
        "tur": "live",
        "type": "basketbol",
        "name": "UNIFACISA - Pinheiros Sao Paulo",
        "time": "01:30",
        "id": "268846656845385728"
    },
    {
        "tur": "live",
        "type": "basketbol",
        "name": "Sao Jose dos Campos (W) - Santo Andre Apaba (W)",
        "time": "01:30",
        "id": "268920877317492736"
    }
]