[
    {
        "tur": "live",
        "type": "futbol",
        "name": "Duque de Caxias - Uniao Central",
        "time": "20:45",
        "id": "275666935285420032"
    },
    {
        "tur": "live",
        "type": "futbol",
        "name": "Stromsgodset (A) - Skjetten",
        "time": "20:30",
        "id": "275220515000553472"
    },
    {
        "tur": "live",
        "type": "futbol",
        "name": "Johor Darul Takzim FC - Valencia CF B",
        "time": "20:00",
        "id": "275630983861112832"
    },
    {
        "tur": "live",
        "type": "futbol",
        "name": "IK Sirius FK - Mjallby AIF",
        "time": "20:00",
        "id": "274745443309719552"
    },
    {
        "tur": "live",
        "type": "futbol",
        "name": "Amanat Baghdad Sc - Naft Al-Basra SC",
        "time": "20:00",
        "id": "275618955245260800"
    },
    {
        "tur": "live",
        "type": "futbol",
        "name": "Assiden - Hamarkameratene Football 2",
        "time": "20:00",
        "id": "275218581831159808"
    },
    {
        "tur": "live",
        "type": "futbol",
        "name": "DFK Dainava Alytus - FK Panevezys",
        "time": "20:00",
        "id": "275218581754613760"
    },
    {
        "tur": "live",
        "type": "futbol",
        "name": "Cesar Vallejo Reserves - Juventus Huamachuco FC",
        "time": "20:00",
        "id": "275732222477209600"
    },
    {
        "tur": "live",
        "type": "futbol",
        "name": "GOSK Gabela - FK Arsenal Tivat",
        "time": "19:30",
        "id": "275719132441350144"
    },
    {
        "tur": "live",
        "type": "futbol",
        "name": "FC Botosani - FC Farul Constanta",
        "time": "19:00",
        "id": "274099158644822016"
    },
    {
        "tur": "live",
        "type": "futbol",
        "name": "NJS - PPJ Helsinki",
        "time": "19:00",
        "id": "275567150069059584"
    },
    {
        "tur": "live",
        "type": "futbol",
        "name": "Amazon Callao FC - Pacifico FC",
        "time": "19:00",
        "id": "275643643815137280"
    },
    {
        "tur": "live",
        "type": "futbol",
        "name": "Universitario de Deportes Reserves - Sport Boys Reserves",
        "time": "19:00",
        "id": "275726774807171072"
    }
]