[
    {
        "tur": "live",
        "type": "futbol",
        "name": "Racing Club - CA River Plate",
        "time": "00:00",
        "id": "282017844655427584"
    },
    {
        "tur": "live",
        "type": "futbol",
        "name": "ADR Jicaral - AD Municipal Liberia",
        "time": "00:00",
        "id": "282835149759221760"
    },
    {
        "tur": "live",
        "type": "futbol",
        "name": "Veraguas United (W) - Deportivo Chiriqui (W)",
        "time": "00:00",
        "id": "282929513502117888"
    },
    {
        "tur": "live",
        "type": "futbol",
        "name": "Santos FC (W) - RB Bragantino (W)",
        "time": "23:00",
        "id": "282830079653089280"
    },
    {
        "tur": "live",
        "type": "futbol",
        "name": "USA U20 - Fransa U20",
        "time": "23:00",
        "id": "282830079534600192"
    },
    {
        "tur": "live",
        "type": "futbol",
        "name": "Colombia U20 - Norveç U20",
        "time": "23:00",
        "id": "282424706091585536"
    }
]