[
    {
        "tur": "live",
        "type": "futbol",
        "name": "Iraklis 1908 FC - Panserraikos",
        "time": "17:30",
        "id": "280520329652211712"
    },
    {
        "tur": "live",
        "type": "futbol",
        "name": "Özbekistan - Kırgızistan",
        "time": "17:30",
        "id": "280347128029646848"
    },
    {
        "tur": "live",
        "type": "futbol",
        "name": "Deportivo Armenio Reserves - CS Dock Sud Reserves",
        "time": "17:00",
        "id": "280503674975948800"
    },
    {
        "tur": "live",
        "type": "futbol",
        "name": "Deportivo Espanol Reserves - Defensores de Cambaceres Reserves",
        "time": "17:00",
        "id": "280503375728087040"
    },
    {
        "tur": "live",
        "type": "futbol",
        "name": "FK Inter Bratislava - MSK Zilina B",
        "time": "17:00",
        "id": "280167091948097536"
    },
    {
        "tur": "live",
        "type": "futbol",
        "name": "Endonezya - Tayvan",
        "time": "16:30",
        "id": "280363200362450944"
    },
    {
        "tur": "live",
        "type": "futbol",
        "name": "Borussia Monchengladbach - Schalke 04",
        "time": "16:00",
        "id": "280439285981777920"
    },
    {
        "tur": "live",
        "type": "futbol",
        "name": "Watford U21 - Sheffield Utd U21",
        "time": "16:00",
        "id": "280439615085744128"
    },
    {
        "tur": "live",
        "type": "futbol",
        "name": "Sacachispas Reserves - Villa Dalmine Reserves",
        "time": "16:00",
        "id": "280504757081214976"
    },
    {
        "tur": "live",
        "type": "futbol",
        "name": "Günay Sudan - Demokratik Kongo Cumhuriyeti",
        "time": "16:00",
        "id": "280333831853182976"
    },
    {
        "tur": "live",
        "type": "futbol",
        "name": "Kenya - Gambia",
        "time": "16:00",
        "id": "280095765559382016"
    },
    {
        "tur": "live",
        "type": "futbol",
        "name": "Namibya - Malavi",
        "time": "16:00",
        "id": "280329236214059008"
    },
    {
        "tur": "live",
        "type": "futbol",
        "name": "Arsenal de Sarandi U20 - All Boys U20",
        "time": "16:00",
        "id": "280536979011145728"
    },
    {
        "tur": "live",
        "type": "futbol",
        "name": "Deportivo Moron U20 - CA Fenix U20",
        "time": "16:00",
        "id": "280537161464418304"
    },
    {
        "tur": "live",
        "type": "futbol",
        "name": "Ferroviario Beira - Baia Pemba",
        "time": "15:45",
        "id": "280518643679367168"
    }
]