[
    {
        "tur": "live",
        "type": "futbol",
        "name": "Asociacion Deportiva Tarma - Sport Huancayo",
        "time": "23:15",
        "id": "277665481419264000"
    },
    {
        "tur": "live",
        "type": "futbol",
        "name": "Excursionistas - CD UAI Urquiza",
        "time": "23:00",
        "id": "277773664100945920"
    },
    {
        "tur": "live",
        "type": "futbol",
        "name": "Botafogo PB - AA Ponte Preta",
        "time": "23:00",
        "id": "277585646115229696"
    },
    {
        "tur": "live",
        "type": "futbol",
        "name": "Cadiz - Cordoba",
        "time": "22:45",
        "id": "278002822704926720"
    },
    {
        "tur": "live",
        "type": "futbol",
        "name": "FC Arouca - AVS Futebol SAD",
        "time": "22:30",
        "id": "277052183083618304"
    },
    {
        "tur": "live",
        "type": "futbol",
        "name": "Real Zaragoza - SD Huesca",
        "time": "22:30",
        "id": "278067199458021376"
    },
    {
        "tur": "live",
        "type": "futbol",
        "name": "Boca Juniors - Racing Club",
        "time": "22:30",
        "id": "276396412794703872"
    },
    {
        "tur": "live",
        "type": "futbol",
        "name": "PSV Eindhoven - Sparta Rotterdam",
        "time": "22:00",
        "id": "275045975457927168"
    },
    {
        "tur": "live",
        "type": "futbol",
        "name": "Palermo - Man City",
        "time": "22:00",
        "id": "277979308166877184"
    },
    {
        "tur": "live",
        "type": "futbol",
        "name": "Valencia CF - Torino FC",
        "time": "22:00",
        "id": "277987147981656064"
    },
    {
        "tur": "live",
        "type": "futbol",
        "name": "Xerez CD - Sanluqueno",
        "time": "22:00",
        "id": "278060971320283136"
    },
    {
        "tur": "live",
        "type": "futbol",
        "name": "America Mineiro MG - Remo PA",
        "time": "22:00",
        "id": "277490267020464128"
    },
    {
        "tur": "live",
        "type": "futbol",
        "name": "Mushuc Runa - Libertad FC",
        "time": "22:00",
        "id": "277581804857331712"
    },
    {
        "tur": "live",
        "type": "futbol",
        "name": "Universidad de Chile - Union Espanola",
        "time": "22:00",
        "id": "277548370657153024"
    },
    {
        "tur": "live",
        "type": "futbol",
        "name": "General Caballero JLM - Sportivo Ameliano",
        "time": "22:00",
        "id": "277581805461311488"
    }
]