[
    {
        "tur": "live",
        "type": "futbol",
        "name": "Melbourne Knights - Hume City",
        "time": "12:30",
        "id": "277072217844617216"
    },
    {
        "tur": "live",
        "type": "futbol",
        "name": "Nunawading City - Werribee City",
        "time": "12:30",
        "id": "277175562127151104"
    },
    {
        "tur": "live",
        "type": "futbol",
        "name": "FC Ucsa Tarasivka - Podillia Khmelnytskyi",
        "time": "12:00",
        "id": "277289957973954560"
    },
    {
        "tur": "live",
        "type": "futbol",
        "name": "Adelaide Comets Reserves (W) - Adelaide University Reserves (W)",
        "time": "11:45",
        "id": "277161807219658752"
    },
    {
        "tur": "live",
        "type": "futbol",
        "name": "Elche - Al Ahli Jeddah",
        "time": "11:30",
        "id": "277299169190875136"
    },
    {
        "tur": "live",
        "type": "futbol",
        "name": "AC Parma - Pro Vercelli",
        "time": "11:30",
        "id": "277155637705707520"
    },
    {
        "tur": "live",
        "type": "futbol",
        "name": "FC Slovan Liberec (W) - AC Sparta Praha II (W)",
        "time": "11:30",
        "id": "277338569992966144"
    },
    {
        "tur": "live",
        "type": "futbol",
        "name": "Altona East Phoenix Reserves - Craigieburn City FC Reserves",
        "time": "11:30",
        "id": "277350126135152640"
    },
    {
        "tur": "live",
        "type": "futbol",
        "name": "Port Melbourne U23 - Dandenong City U23",
        "time": "11:15",
        "id": "277161049972674560"
    },
    {
        "tur": "live",
        "type": "futbol",
        "name": "Oakleigh Cannons U23 - Altona Magic U23",
        "time": "11:15",
        "id": "277157847466381312"
    },
    {
        "tur": "live",
        "type": "futbol",
        "name": "Deportiva Minera - Athletic Club Torrellano",
        "time": "11:00",
        "id": "277294503116804096"
    },
    {
        "tur": "live",
        "type": "futbol",
        "name": "Blacktown Spartans U20 - Inter Lions U20",
        "time": "11:00",
        "id": "277335664869117952"
    },
    {
        "tur": "live",
        "type": "futbol",
        "name": "Broadmeadow Magic FC Reserves - Valentine Phoenix Reserves",
        "time": "11:00",
        "id": "277180734419111936"
    },
    {
        "tur": "live",
        "type": "futbol",
        "name": "Glenorchy Knights U21 - South Hobart U21",
        "time": "11:00",
        "id": "277164542887333888"
    }
]