[
    {
        "tur": "live",
        "type": "futbol",
        "name": "Singapur (Kadınlar) - Iran (W)",
        "time": "16:00",
        "id": "275266558761242624"
    },
    {
        "tur": "live",
        "type": "futbol",
        "name": "Silver Strikers - MAFCO",
        "time": "15:30",
        "id": "275232265228914688"
    },
    {
        "tur": "live",
        "type": "futbol",
        "name": "Arema Endonezya - Oxford United",
        "time": "15:30",
        "id": "275193165098651648"
    },
    {
        "tur": "live",
        "type": "futbol",
        "name": "FK Ekibastuz - Khan Tengri FC",
        "time": "15:00",
        "id": "275126808986390528"
    },
    {
        "tur": "live",
        "type": "futbol",
        "name": "Osun United - Kun Khalifat FC",
        "time": "15:00",
        "id": "275234382022840320"
    },
    {
        "tur": "live",
        "type": "futbol",
        "name": "Warri Wolves - Crown FC",
        "time": "15:00",
        "id": "275357583634731008"
    },
    {
        "tur": "live",
        "type": "futbol",
        "name": "Cotonsport de Garoua - Aigle Royal De La Menoua (Dschang)",
        "time": "15:00",
        "id": "275369938634543104"
    },
    {
        "tur": "live",
        "type": "futbol",
        "name": "Aigle Royal du Moungo - Bafmeng United",
        "time": "15:00",
        "id": "275370063108902912"
    }
]