[
    {
        "tur": "live",
        "type": "futbol",
        "name": "Adelaide Croatia Raiders - North Eastern Metro Stars",
        "time": "08:30",
        "id": "272508212941557760"
    },
    {
        "tur": "live",
        "type": "futbol",
        "name": "Playford Patriots - Campbelltown City",
        "time": "08:30",
        "id": "272508213295976448"
    },
    {
        "tur": "live",
        "type": "futbol",
        "name": "Cooks Hill United - Belmont Swansea United FC",
        "time": "08:30",
        "id": "272508221267251200"
    },
    {
        "tur": "live",
        "type": "futbol",
        "name": "Altona Magic - Hume City",
        "time": "08:15",
        "id": "272508215513714688"
    },
    {
        "tur": "live",
        "type": "futbol",
        "name": "Gold Coast United - Brisbane City",
        "time": "08:15",
        "id": "272617456243183616"
    },
    {
        "tur": "live",
        "type": "futbol",
        "name": "Eastern Lions U23 - Moreland City U23",
        "time": "08:15",
        "id": "272815023223607296"
    },
    {
        "tur": "live",
        "type": "futbol",
        "name": "Avondale Fc - St Albans Saints Sc",
        "time": "08:00",
        "id": "272508215580823552"
    },
    {
        "tur": "live",
        "type": "futbol",
        "name": "Western Sydney Wanderers NPL - Sydney United",
        "time": "08:00",
        "id": "272619230882566144"
    },
    {
        "tur": "live",
        "type": "futbol",
        "name": "Giravanz Kitakyushu - Azul Claro Numazu",
        "time": "08:00",
        "id": "272508226625474560"
    },
    {
        "tur": "live",
        "type": "futbol",
        "name": "Langwarrin Sc - Manningham United Blues",
        "time": "08:00",
        "id": "272728521101676544"
    },
    {
        "tur": "live",
        "type": "futbol",
        "name": "Croydon Kings - Adelaide Comets",
        "time": "08:00",
        "id": "272508213090455552"
    },
    {
        "tur": "live",
        "type": "futbol",
        "name": "Boroondara Carey Eagles - Eltham Redbacks",
        "time": "08:00",
        "id": "272739859883495424"
    },
    {
        "tur": "live",
        "type": "futbol",
        "name": "Marlin Coast Rangers - Peninsula Power",
        "time": "07:00",
        "id": "272915207060328448"
    },
    {
        "tur": "live",
        "type": "futbol",
        "name": "Tiamo Hirakata - Okinawa Sv",
        "time": "07:00",
        "id": "272867324162347008"
    },
    {
        "tur": "live",
        "type": "futbol",
        "name": "Maruyasu Industries SC - Asuka FC",
        "time": "07:00",
        "id": "272867247130808320"
    }
]