[
    {
        "tur": "live",
        "type": "futbol",
        "name": "Deportes Tolima - Boyaca Chico",
        "time": "04:30",
        "id": "280690818043482112"
    },
    {
        "tur": "live",
        "type": "futbol",
        "name": "Atletico de San Luis - Club Tijuana Xoloitzcuintles de Caliente",
        "time": "04:00",
        "id": "280088940104519680"
    },
    {
        "tur": "live",
        "type": "futbol",
        "name": "Pachuca (W) - Necaxa (W)",
        "time": "04:00",
        "id": "280866057837744128"
    },
    {
        "tur": "live",
        "type": "futbol",
        "name": "North Texas SC - Swope Park Rangers",
        "time": "03:30",
        "id": "280864099851702272"
    },
    {
        "tur": "live",
        "type": "futbol",
        "name": "CD Irapuato - CD Tepatitlan de Morelos",
        "time": "03:00",
        "id": "280761104813133824"
    },
    {
        "tur": "live",
        "type": "futbol",
        "name": "Montego Bay United - Tivoli Gardens",
        "time": "03:00",
        "id": "281315774221651968"
    }
]