[
    {
        "tur": "live",
        "type": "futbol",
        "name": "Vietnam (Kadınlar) - Cambodia (W)",
        "time": "15:30",
        "id": "277706551516598272"
    },
    {
        "tur": "live",
        "type": "futbol",
        "name": "Jordan U20 (W) - Northern Mariana Islands U20 (W)",
        "time": "15:30",
        "id": "277759436043456512"
    },
    {
        "tur": "live",
        "type": "futbol",
        "name": "Hamarkameratene U19 - Viking U19",
        "time": "14:30",
        "id": "277744125903769600"
    },
    {
        "tur": "live",
        "type": "futbol",
        "name": "Royal AM FC (W) - Richmond (W)",
        "time": "14:00",
        "id": "277745272965173248"
    },
    {
        "tur": "live",
        "type": "futbol",
        "name": "Balcatta (W) - Perth Redstar FC (W)",
        "time": "14:00",
        "id": "277702424542711808"
    },
    {
        "tur": "live",
        "type": "futbol",
        "name": "Kashima Antlers - Avispa Fukuoka",
        "time": "13:00",
        "id": "277628136300089344"
    }
]