[
    {
        "tur": "live",
        "type": "futbol",
        "name": "Hong Kong U23 - Guam U23",
        "time": "17:30",
        "id": "280905358273286144"
    },
    {
        "tur": "live",
        "type": "futbol",
        "name": "Banik Kalinovo - FC Vion Zlate Moravce",
        "time": "17:30",
        "id": "280727206431428608"
    },
    {
        "tur": "live",
        "type": "futbol",
        "name": "Azerbaycan U21 - Bulgaristan U21",
        "time": "17:00",
        "id": "280710510205341696"
    },
    {
        "tur": "live",
        "type": "futbol",
        "name": "Club Comunicaciones Reserves - Deportivo Laferrere Reserves",
        "time": "17:00",
        "id": "280892459127541760"
    },
    {
        "tur": "live",
        "type": "futbol",
        "name": "Kyrgyzstan U23 - Sri Lanka U23",
        "time": "17:00",
        "id": "280710511034765312"
    },
    {
        "tur": "live",
        "type": "futbol",
        "name": "Utsiktens BK U21 - Falkenberg U21",
        "time": "17:00",
        "id": "280901789522464768"
    },
    {
        "tur": "live",
        "type": "futbol",
        "name": "Armenia U21 - Polonya U21",
        "time": "16:00",
        "id": "280775416302669824"
    },
    {
        "tur": "live",
        "type": "futbol",
        "name": "Macaristan U19 - Karadağ U19",
        "time": "16:00",
        "id": "280797655107506176"
    },
    {
        "tur": "live",
        "type": "futbol",
        "name": "Sierra Leone - Etiyopya",
        "time": "16:00",
        "id": "280458274581647360"
    },
    {
        "tur": "live",
        "type": "futbol",
        "name": "Zimbabve - Ruanda",
        "time": "16:00",
        "id": "280458274811285504"
    },
    {
        "tur": "live",
        "type": "futbol",
        "name": "Kenya - Seyşel Adaları",
        "time": "16:00",
        "id": "280095765908557824"
    },
    {
        "tur": "live",
        "type": "futbol",
        "name": "Namibya - Sao Tome and Principe",
        "time": "16:00",
        "id": "280458274690699264"
    },
    {
        "tur": "live",
        "type": "futbol",
        "name": "Tanzanya - Nijer",
        "time": "16:00",
        "id": "280458274447429632"
    },
    {
        "tur": "live",
        "type": "futbol",
        "name": "Chinese Taipei U23 - Bhutan U23",
        "time": "16:00",
        "id": "280719646141845504"
    },
    {
        "tur": "live",
        "type": "futbol",
        "name": "Tayland U23 - Malaysia U23",
        "time": "15:30",
        "id": "280719645577711616"
    }
]