[
    {
        "tur": "live",
        "type": "futbol",
        "name": "Colorado Rapids - Austin FC",
        "time": "04:30",
        "id": "271801176470720512"
    },
    {
        "tur": "live",
        "type": "futbol",
        "name": "FC Leones - Deportivo Pereira",
        "time": "04:20",
        "id": "272107525756817408"
    },
    {
        "tur": "live",
        "type": "futbol",
        "name": "San Antonio Fc - Las Vegas Lights",
        "time": "04:00",
        "id": "271956092775436288"
    },
    {
        "tur": "live",
        "type": "futbol",
        "name": "Colorado Springs Switchbacks Fc - New Mexico United",
        "time": "04:00",
        "id": "266222793446789120"
    },
    {
        "tur": "live",
        "type": "futbol",
        "name": "Leones Negros Guadalajara - CD Tapatio",
        "time": "04:00",
        "id": "271931562794291200"
    },
    {
        "tur": "live",
        "type": "futbol",
        "name": "City SC San Diego - Stars FC",
        "time": "04:00",
        "id": "272429102168936448"
    },
    {
        "tur": "live",
        "type": "futbol",
        "name": "MetaSport FC (W) - La Roca FC (W)",
        "time": "04:00",
        "id": "272296709490610176"
    },
    {
        "tur": "live",
        "type": "futbol",
        "name": "Louisville City FC - Tampa Bay Rowdies",
        "time": "03:00",
        "id": "271956085292797952"
    },
    {
        "tur": "live",
        "type": "futbol",
        "name": "Houston Dynamo II - Swope Park Rangers",
        "time": "03:00",
        "id": "271889184777703424"
    },
    {
        "tur": "live",
        "type": "futbol",
        "name": "Rochester FC - River Light FC",
        "time": "03:00",
        "id": "272035547436945408"
    },
    {
        "tur": "live",
        "type": "futbol",
        "name": "La Equidad - Bogota FC",
        "time": "03:00",
        "id": "272107525670834176"
    },
    {
        "tur": "live",
        "type": "futbol",
        "name": "Forward Madison FC - Union Omaha",
        "time": "03:00",
        "id": "272293986426818560"
    },
    {
        "tur": "live",
        "type": "futbol",
        "name": "Annapolis Blues FC - Lionsbridge FC",
        "time": "02:30",
        "id": "271891139260452864"
    },
    {
        "tur": "live",
        "type": "futbol",
        "name": "South Georgia Tormenta FC - Charlotte Independence",
        "time": "02:30",
        "id": "272293986355515392"
    },
    {
        "tur": "live",
        "type": "futbol",
        "name": "Greenville Triumph Sc - FC Naples",
        "time": "02:00",
        "id": "272293972258459648"
    }
]